myome_ensembl_query/__init__.py
myome_ensembl_query/api_calls.py
myome_ensembl_query/test_api_calls.py
myome_ensembl_query-0.0.1.dist-info/METADATA
myome_ensembl_query-0.0.1.dist-info/WHEEL
myome_ensembl_query-0.0.1.dist-info/entry_points.txt
myome_ensembl_query-0.0.1.dist-info/top_level.txt
myome_ensembl_query-0.0.1.dist-info/RECORD
