Metadata-Version: 2.1
Name: myome-ensembl-query
Version: 0.0.1
Requires-Dist: requests
Requires-Dist: pytest ; python_version == "3.10"
